httpx_ratelimiter/__init__.py
httpx_ratelimiter/httpx_ratelimiter.py
httpx_ratelimiter-0.0.4.dist-info/LICENSE
httpx_ratelimiter-0.0.4.dist-info/WHEEL
httpx_ratelimiter-0.0.4.dist-info/METADATA
httpx_ratelimiter-0.0.4.dist-info/RECORD
