Metadata-Version: 2.1
Name: httpx_ratelimiter
Version: 0.0.4
Summary: Ratelimiting for httpx
Keywords: httpx,rate-limiting,leaky-bucket
Author-email: Anatoly Raev <cralixraev@gmail.com>
Requires-Python: >3.9
Classifier: Development Status :: 4 - Beta
Classifier: Intended Audience :: Developers
Classifier: Typing :: Typed
Requires-Dist: httpx
Requires-Dist: pyrate-limiter~=3.1.0
Requires-Dist: pre-commit ; extra == "dev"
Project-URL: Home, https://github.com/CralixRaev/httpx_ratelimiter
Provides-Extra: dev
